ros_rosidl_typesupport_cpp-3.3.3.data/data/include/rosidl_typesupport_cpp/rosidl_typesupport_cpp/identifier.hpp
ros_rosidl_typesupport_cpp-3.3.3.data/data/include/rosidl_typesupport_cpp/rosidl_typesupport_cpp/message_type_support_dispatch.hpp
ros_rosidl_typesupport_cpp-3.3.3.data/data/include/rosidl_typesupport_cpp/rosidl_typesupport_cpp/service_type_support_dispatch.hpp
ros_rosidl_typesupport_cpp-3.3.3.data/data/include/rosidl_typesupport_cpp/rosidl_typesupport_cpp/type_support_map.h
ros_rosidl_typesupport_cpp-3.3.3.data/data/include/rosidl_typesupport_cpp/rosidl_typesupport_cpp/visibility_control.h
ros_rosidl_typesupport_cpp-3.3.3.data/data/lib/librosidl_typesupport_cpp.so
ros_rosidl_typesupport_cpp-3.3.3.data/data/lib/python3.10/site-packages/rosidl_typesupport_cpp/__init__.py
ros_rosidl_typesupport_cpp-3.3.3.data/data/lib/python3.10/site-packages/rosidl_typesupport_cpp/cli.py
ros_rosidl_typesupport_cpp-3.3.3.data/data/lib/python3.10/site-packages/rosidl_typesupport_cpp/__pycache__/__init__.cpython-310.pyc
ros_rosidl_typesupport_cpp-3.3.3.data/data/lib/python3.10/site-packages/rosidl_typesupport_cpp/__pycache__/cli.cpython-310.pyc
ros_rosidl_typesupport_cpp-3.3.3.data/data/lib/python3.10/site-packages/rosidl_typesupport_cpp-3.3.3-py3.10.egg-info/PKG-INFO
ros_rosidl_typesupport_cpp-3.3.3.data/data/lib/python3.10/site-packages/rosidl_typesupport_cpp-3.3.3-py3.10.egg-info/SOURCES.txt
ros_rosidl_typesupport_cpp-3.3.3.data/data/lib/python3.10/site-packages/rosidl_typesupport_cpp-3.3.3-py3.10.egg-info/dependency_links.txt
ros_rosidl_typesupport_cpp-3.3.3.data/data/lib/python3.10/site-packages/rosidl_typesupport_cpp-3.3.3-py3.10.egg-info/entry_points.txt
ros_rosidl_typesupport_cpp-3.3.3.data/data/lib/python3.10/site-packages/rosidl_typesupport_cpp-3.3.3-py3.10.egg-info/top_level.txt
ros_rosidl_typesupport_cpp-3.3.3.data/data/lib/rosidl_typesupport_cpp/rosidl_typesupport_cpp
ros_rosidl_typesupport_cpp-3.3.3.data/data/share/ament_index/resource_index/package_run_dependencies/rosidl_typesupport_cpp
ros_rosidl_typesupport_cpp-3.3.3.data/data/share/ament_index/resource_index/packages/rosidl_typesupport_cpp
ros_rosidl_typesupport_cpp-3.3.3.data/data/share/ament_index/resource_index/parent_prefix_path/rosidl_typesupport_cpp
ros_rosidl_typesupport_cpp-3.3.3.data/data/share/ament_index/resource_index/rosidl_runtime_packages/rosidl_typesupport_cpp
ros_rosidl_typesupport_cpp-3.3.3.data/data/share/rosidl_typesupport_cpp/local_setup.bash
ros_rosidl_typesupport_cpp-3.3.3.data/data/share/rosidl_typesupport_cpp/local_setup.dsv
ros_rosidl_typesupport_cpp-3.3.3.data/data/share/rosidl_typesupport_cpp/local_setup.sh
ros_rosidl_typesupport_cpp-3.3.3.dist-info/METADATA
ros_rosidl_typesupport_cpp-3.3.3.dist-info/WHEEL
ros_rosidl_typesupport_cpp-3.3.3.dist-info/entry_points.txt
ros_rosidl_typesupport_cpp-3.3.3.dist-info/top_level.txt
ros_rosidl_typesupport_cpp-3.3.3.dist-info/RECORD
