Metadata-Version: 2.4
Name: ros-rosidl-typesupport-cpp
Version: 3.3.3
Summary: A ROS package for accessing C++ typesupport handler functions for ROS messages and services.
Requires-Dist: ros-ament-index-python~=1.11.0
Requires-Dist: ros-rosidl-pycommon~=4.9.5
Requires-Dist: ros-rosidl-runtime-c~=4.9.5
Requires-Dist: ros-rosidl-typesupport-interface~=4.9.5
Requires-Dist: ros-rosidl-generator-c~=4.9.5
Requires-Dist: ros-rcpputils~=2.13.5
Requires-Dist: ros-rosidl-cli~=4.9.5
Requires-Dist: ros-rosidl-generator-type-description~=4.9.5
Requires-Dist: ros-rcutils~=6.9.8
Requires-Dist: ros-rosidl-typesupport-c~=3.3.3
Requires-Dist: ros-rosidl-runtime-cpp~=4.9.5
Dynamic: description
Dynamic: description-content-type
Dynamic: requires-dist
Dynamic: summary
